[
  {
      "id" : 1,
      "cover": "cheche.jpeg",
      "sound" : "La-Chenille-Synchro-la-Cheu-Cheu.mp3",
      "title" : "La-Chenille-Synchro",
      "category" : "Paillarde"
  },
  {
      "id" : 2,
      "cover" : "disney.jpeg",
      "sound" : "ready_for_the_ride__from.mp3",
      "title" : "Ready For The Ride",
      "category" : "Enfant"
  },
  {
      "id" : 3,
      "cover" : "muse.png",
      "sound" : "Soolking ft.-Gazo-Casanova.mp3",
      "title" : "Casanova",
      "category" : "Pop"
  },
  {
      "id" : 4,
      "cover" : "muse.png",
      "sound" : "Bigflo-Oli-Sur-la-lune.mp3",
      "title" : "Sur la lune Big flo et Oli",
      "category" : "Rap"
  },
  {
    "id" : 5,
    "cover" : "Boris.jpg",
    "sound" : "Boris - Soirée disco.mp3",
    "title" : "Boris - Soirée disco",
    "category" : "Paillard"
},
{
    "id" : 6,
    "cover" : "etait.jpg",
    "sound" : "The Shin Sekai - Si jétais (Officiel).mp3",
    "title" : "Si j'étais",
    "category" : "Rap"
}


]